wpdatautil/__init__.py
wpdatautil/dict.py
wpdatautil/humanfriendly.py
wpdatautil/inspect.py
wpdatautil/list.py
wpdatautil/mgzip.py
wpdatautil/numpy.py
wpdatautil/object.py
wpdatautil/pathlib.py
wpdatautil/textwrap.py
wpdatautil/timeit.py
wpdatautil/awswrangler/__init__.py
wpdatautil/awswrangler/athena.py
wpdatautil/awswrangler/catalog.py
wpdatautil/boto3/__init__.py
wpdatautil/boto3/glue.py
wpdatautil/logging/__init__.py
wpdatautil/logging/psutil.py
wpdatautil/pandas/__init__.py
wpdatautil/pandas/mgzip.py
wpdatautil/pandas/numpy.py
wpdatautil/pandas/pyarrow.py
wpdatautil/pandas/pybase64.py
wpdatautil/pandas/smart_open.py
wpdatautil/s3path/__init__.py
wpdatautil/s3path/boto3.py
wpdatautil/str/__init__.py
wpdatautil/str/sql/__init__.py
wpdatautil/str/sql/presto.py
wpdatautil-0.9.2.dist-info/LICENSE
wpdatautil-0.9.2.dist-info/METADATA
wpdatautil-0.9.2.dist-info/WHEEL
wpdatautil-0.9.2.dist-info/top_level.txt
wpdatautil-0.9.2.dist-info/RECORD
