Metadata-Version: 2.1
Name: wpdatautil
Version: 0.9.2
Summary: Utility functions for data processing
Home-page: UNKNOWN
Author: Data Util
Author-email: user@users.nomail.github.com
License: UNKNOWN
Keywords: utilities
Platform: UNKNOWN
Classifier: Programming Language :: Python :: 3.8
Classifier: Programming Language :: Python :: 3.9
Classifier: License :: OSI Approved :: MIT License
Classifier: Topic :: Software Development :: Libraries :: Python Modules
Classifier: Topic :: Utilities
Requires-Python: >=3.8
License-File: LICENSE
